django_opensearch_toolkit/__init__.py
django_opensearch_toolkit/apps.py
django_opensearch_toolkit/py.typed
django_opensearch_toolkit/management/__init__.py
django_opensearch_toolkit/management/commands/__init__.py
django_opensearch_toolkit/management/commands/_opensearch_command.py
django_opensearch_toolkit/management/commands/opensearch_displaymigrations.py
django_opensearch_toolkit/management/commands/opensearch_runmigrations.py
django_opensearch_toolkit/migration_manager/__init__.py
django_opensearch_toolkit/migration_manager/migration_log.py
django_opensearch_toolkit/migration_manager/migration_manager.py
django_opensearch_toolkit/migration_manager/opensearch_migration.py
django_opensearch_toolkit/unittest/__init__.py
django_opensearch_toolkit/unittest/base_tests.py
django_opensearch_toolkit-0.1.0.dist-info/LICENSE
django_opensearch_toolkit-0.1.0.dist-info/METADATA
django_opensearch_toolkit-0.1.0.dist-info/WHEEL
django_opensearch_toolkit-0.1.0.dist-info/top_level.txt
django_opensearch_toolkit-0.1.0.dist-info/RECORD
