Metadata-Version: 2.1
Name: django-opensearch-toolkit
Version: 0.1.0
Summary: A Django app for interacting with OpenSearch clusters
Author-email: David Tagliamonti <dtag@ambient.ai>
License: MIT License
Project-URL: Homepage, https://github.com/AmbientAI/django-opensearch-toolkit
Project-URL: Repository, https://github.com/AmbientAI/django-opensearch-toolkit
Project-URL: Issues, https://github.com/AmbientAI/django-opensearch-toolkit/issues
Project-URL: Changelog, https://github.com/AmbientAI/django-opensearch-toolkit/blob/main/CHANGELOG.md
Classifier: Environment :: Web Environment
Classifier: Framework :: Django
Classifier: Intended Audience :: Developers
Classifier: Programming Language :: Python :: 3
Classifier: Programming Language :: Python :: 3.9
Classifier: Programming Language :: Python :: 3.10
Classifier: Programming Language :: Python :: 3.11
Classifier: Programming Language :: Python :: 3.12
Classifier: Programming Language :: Python :: 3.13
Classifier: Operating System :: OS Independent
Classifier: Typing :: Typed
Requires-Python: >=3.9
License-File: LICENSE
Requires-Dist: django >=4.2.14
Requires-Dist: django-stubs >=4.2.7
Requires-Dist: opensearch-py >=2.7.1
Requires-Dist: openmock >=2.2.0
